msgpacku.py
msgpacku-0.2.0.dist-info/DESCRIPTION.rst
msgpacku-0.2.0.dist-info/METADATA
msgpacku-0.2.0.dist-info/RECORD
msgpacku-0.2.0.dist-info/WHEEL
msgpacku-0.2.0.dist-info/metadata.json
msgpacku-0.2.0.dist-info/top_level.txt
